{
  "status": "ok",
  "version": 2,
  "last_updated": "2026-06-12T05:55:54.247362+00:00",
  "location": {
    "name": "L'Ametlla de Mar - Zona Gàbies",
    "min_lat": 40.8,
    "max_lat": 40.9,
    "min_lon": 0.8,
    "max_lon": 0.9
  },
  "depths": [
    0,
    10,
    20,
    30,
    40
  ],
  "period": {
    "start": "2026-06-09",
    "end": "2026-06-17"
  },
  "current": {
    "surface": {
      "temperature": 23.65,
      "salinity": 37.9,
      "current_speed": 0.058,
      "current_direction": 239.0,
      "current_direction_label": "SO",
      "oxygen": 243.73,
      "chlorophyll": 0.06,
      "nitrate": 0.32,
      "phosphate": 0.01
    },
    "10m": {
      "temperature": 20.64,
      "salinity": 37.87,
      "current_speed": 0.051,
      "current_direction": 191.3,
      "current_direction_label": "S",
      "oxygen": 243.74,
      "chlorophyll": 0.06,
      "nitrate": 0.32,
      "phosphate": 0.01
    },
    "20m": {
      "temperature": 19.72,
      "salinity": 37.92,
      "current_speed": 0.04,
      "current_direction": 180.0,
      "current_direction_label": "S",
      "oxygen": 244.16,
      "chlorophyll": 0.07,
      "nitrate": 0.38,
      "phosphate": 0.01
    },
    "30m": {
      "temperature": 18.41,
      "salinity": 37.97,
      "current_speed": 0.032,
      "current_direction": 161.6,
      "current_direction_label": "S",
      "oxygen": 250.43,
      "chlorophyll": 0.1,
      "nitrate": 0.22,
      "phosphate": 0.01
    },
    "40m": {
      "temperature": 17.31,
      "salinity": 38.03,
      "current_speed": 0.022,
      "current_direction": 116.6,
      "current_direction_label": "SE",
      "oxygen": 253.35,
      "chlorophyll": 0.17,
      "nitrate": 0.07,
      "phosphate": 0.01
    }
  },
  "mixed_layer_depth": 11.75,
  "daily": [
    {
      "date": "2026-06-09",
      "is_forecast": false,
      "surface": {
        "temperature": 22.46,
        "salinity": 37.9,
        "current_speed": 0.032,
        "current_direction": 198.4,
        "oxygen": 249.86,
        "chlorophyll": 0.11,
        "nitrate": 0.85,
        "phosphate": 0.03
      },
      "10m": {
        "temperature": 19.2,
        "salinity": 38.01,
        "current_speed": 0.03,
        "current_direction": 180.0,
        "oxygen": 249.88,
        "chlorophyll": 0.11,
        "nitrate": 0.85,
        "phosphate": 0.03
      },
      "20m": {
        "temperature": 17.92,
        "salinity": 38.07,
        "current_speed": 0.01,
        "current_direction": 180.0,
        "oxygen": 252.02,
        "chlorophyll": 0.14,
        "nitrate": 0.48,
        "phosphate": 0.02
      },
      "30m": {
        "temperature": 16.96,
        "salinity": 38.1,
        "current_speed": 0.01,
        "current_direction": 180.0,
        "oxygen": 253.12,
        "chlorophyll": 0.19,
        "nitrate": 0.07,
        "phosphate": 0.01
      },
      "40m": {
        "temperature": 16.26,
        "salinity": 38.12,
        "current_speed": 0.0,
        "current_direction": 180.0,
        "oxygen": 251.71,
        "chlorophyll": 0.26,
        "nitrate": 0.04,
        "phosphate": 0.02
      },
      "mixed_layer_depth": 11.75
    },
    {
      "date": "2026-06-10",
      "is_forecast": false,
      "surface": {
        "temperature": 21.98,
        "salinity": 37.95,
        "current_speed": 0.071,
        "current_direction": 171.9,
        "oxygen": 252.63,
        "chlorophyll": 0.11,
        "nitrate": 0.54,
        "phosphate": 0.03
      },
      "10m": {
        "temperature": 19.56,
        "salinity": 37.99,
        "current_speed": 0.01,
        "current_direction": 180.0,
        "oxygen": 252.69,
        "chlorophyll": 0.11,
        "nitrate": 0.54,
        "phosphate": 0.03
      },
      "20m": {
        "temperature": 18.03,
        "salinity": 38.07,
        "current_speed": 0.03,
        "current_direction": 180.0,
        "oxygen": 255.92,
        "chlorophyll": 0.15,
        "nitrate": 0.38,
        "phosphate": 0.02
      },
      "30m": {
        "temperature": 17.02,
        "salinity": 38.09,
        "current_speed": 0.02,
        "current_direction": 180.0,
        "oxygen": 255.44,
        "chlorophyll": 0.21,
        "nitrate": 0.06,
        "phosphate": 0.01
      },
      "40m": {
        "temperature": 16.3,
        "salinity": 38.11,
        "current_speed": 0.022,
        "current_direction": 153.4,
        "oxygen": 253.47,
        "chlorophyll": 0.26,
        "nitrate": 0.04,
        "phosphate": 0.02
      },
      "mixed_layer_depth": 11.75
    },
    {
      "date": "2026-06-11",
      "is_forecast": false,
      "surface": {
        "temperature": 20.92,
        "salinity": 37.94,
        "current_speed": 0.122,
        "current_direction": 170.5,
        "oxygen": 249.28,
        "chlorophyll": 0.09,
        "nitrate": 0.38,
        "phosphate": 0.02
      },
      "10m": {
        "temperature": 19.85,
        "salinity": 37.95,
        "current_speed": 0.032,
        "current_direction": 251.6,
        "oxygen": 249.37,
        "chlorophyll": 0.09,
        "nitrate": 0.38,
        "phosphate": 0.02
      },
      "20m": {
        "temperature": 18.18,
        "salinity": 38.05,
        "current_speed": 0.01,
        "current_direction": 180.0,
        "oxygen": 255.6,
        "chlorophyll": 0.13,
        "nitrate": 0.31,
        "phosphate": 0.02
      },
      "30m": {
        "temperature": 17.16,
        "salinity": 38.08,
        "current_speed": 0.02,
        "current_direction": 180.0,
        "oxygen": 255.81,
        "chlorophyll": 0.19,
        "nitrate": 0.06,
        "phosphate": 0.01
      },
      "40m": {
        "temperature": 16.42,
        "salinity": 38.11,
        "current_speed": 0.014,
        "current_direction": 135.0,
        "oxygen": 254.09,
        "chlorophyll": 0.25,
        "nitrate": 0.03,
        "phosphate": 0.02
      },
      "mixed_layer_depth": 11.74
    },
    {
      "date": "2026-06-12",
      "is_forecast": false,
      "surface": {
        "temperature": 20.75,
        "salinity": 37.95,
        "current_speed": 0.042,
        "current_direction": 135.0,
        "oxygen": 247.46,
        "chlorophyll": 0.09,
        "nitrate": 0.37,
        "phosphate": 0.02
      },
      "10m": {
        "temperature": 19.82,
        "salinity": 37.93,
        "current_speed": 0.036,
        "current_direction": 213.7,
        "oxygen": 247.47,
        "chlorophyll": 0.09,
        "nitrate": 0.37,
        "phosphate": 0.02
      },
      "20m": {
        "temperature": 18.26,
        "salinity": 38.02,
        "current_speed": 0.051,
        "current_direction": 191.3,
        "oxygen": 254.89,
        "chlorophyll": 0.12,
        "nitrate": 0.27,
        "phosphate": 0.02
      },
      "30m": {
        "temperature": 17.34,
        "salinity": 38.06,
        "current_speed": 0.051,
        "current_direction": 168.7,
        "oxygen": 256.05,
        "chlorophyll": 0.17,
        "nitrate": 0.07,
        "phosphate": 0.01
      },
      "40m": {
        "temperature": 16.62,
        "salinity": 38.09,
        "current_speed": 0.036,
        "current_direction": 146.3,
        "oxygen": 254.56,
        "chlorophyll": 0.23,
        "nitrate": 0.03,
        "phosphate": 0.01
      },
      "mixed_layer_depth": 11.72
    },
    {
      "date": "2026-06-13",
      "is_forecast": true,
      "surface": {
        "temperature": 21.3,
        "salinity": 37.92,
        "current_speed": 0.054,
        "current_direction": 201.8,
        "oxygen": 247.15,
        "chlorophyll": 0.09,
        "nitrate": 0.38,
        "phosphate": 0.02
      },
      "10m": {
        "temperature": 19.74,
        "salinity": 37.91,
        "current_speed": 0.061,
        "current_direction": 189.5,
        "oxygen": 247.15,
        "chlorophyll": 0.09,
        "nitrate": 0.38,
        "phosphate": 0.02
      },
      "20m": {
        "temperature": 18.55,
        "salinity": 37.97,
        "current_speed": 0.051,
        "current_direction": 191.3,
        "oxygen": 252.33,
        "chlorophyll": 0.11,
        "nitrate": 0.31,
        "phosphate": 0.02
      },
      "30m": {
        "temperature": 17.65,
        "salinity": 38.02,
        "current_speed": 0.051,
        "current_direction": 168.7,
        "oxygen": 255.56,
        "chlorophyll": 0.15,
        "nitrate": 0.12,
        "phosphate": 0.01
      },
      "40m": {
        "temperature": 16.92,
        "salinity": 38.07,
        "current_speed": 0.014,
        "current_direction": 135.0,
        "oxygen": 254.67,
        "chlorophyll": 0.21,
        "nitrate": 0.03,
        "phosphate": 0.01
      },
      "mixed_layer_depth": 11.73
    },
    {
      "date": "2026-06-14",
      "is_forecast": true,
      "surface": {
        "temperature": 22.23,
        "salinity": 37.88,
        "current_speed": 0.022,
        "current_direction": 243.4,
        "oxygen": 246.36,
        "chlorophyll": 0.08,
        "nitrate": 0.38,
        "phosphate": 0.02
      },
      "10m": {
        "temperature": 19.94,
        "salinity": 37.89,
        "current_speed": 0.051,
        "current_direction": 191.3,
        "oxygen": 246.36,
        "chlorophyll": 0.08,
        "nitrate": 0.38,
        "phosphate": 0.02
      },
      "20m": {
        "temperature": 18.89,
        "salinity": 37.94,
        "current_speed": 0.04,
        "current_direction": 180.0,
        "oxygen": 249.75,
        "chlorophyll": 0.1,
        "nitrate": 0.36,
        "phosphate": 0.02
      },
      "30m": {
        "temperature": 17.86,
        "salinity": 38.0,
        "current_speed": 0.032,
        "current_direction": 161.6,
        "oxygen": 254.64,
        "chlorophyll": 0.14,
        "nitrate": 0.15,
        "phosphate": 0.01
      },
      "40m": {
        "temperature": 17.08,
        "salinity": 38.05,
        "current_speed": 0.01,
        "current_direction": 90.0,
        "oxygen": 254.21,
        "chlorophyll": 0.21,
        "nitrate": 0.04,
        "phosphate": 0.01
      },
      "mixed_layer_depth": 11.74
    },
    {
      "date": "2026-06-15",
      "is_forecast": true,
      "surface": {
        "temperature": 22.96,
        "salinity": 37.88,
        "current_speed": 0.01,
        "current_direction": 180.0,
        "oxygen": 245.56,
        "chlorophyll": 0.07,
        "nitrate": 0.35,
        "phosphate": 0.01
      },
      "10m": {
        "temperature": 20.12,
        "salinity": 37.88,
        "current_speed": 0.03,
        "current_direction": 180.0,
        "oxygen": 245.56,
        "chlorophyll": 0.07,
        "nitrate": 0.35,
        "phosphate": 0.01
      },
      "20m": {
        "temperature": 19.09,
        "salinity": 37.93,
        "current_speed": 0.02,
        "current_direction": 180.0,
        "oxygen": 248.26,
        "chlorophyll": 0.09,
        "nitrate": 0.37,
        "phosphate": 0.02
      },
      "30m": {
        "temperature": 17.87,
        "salinity": 38.0,
        "current_speed": 0.01,
        "current_direction": 180.0,
        "oxygen": 253.92,
        "chlorophyll": 0.14,
        "nitrate": 0.15,
        "phosphate": 0.01
      },
      "40m": {
        "temperature": 17.1,
        "salinity": 38.05,
        "current_speed": 0.0,
        "current_direction": 180.0,
        "oxygen": 253.74,
        "chlorophyll": 0.21,
        "nitrate": 0.04,
        "phosphate": 0.01
      },
      "mixed_layer_depth": 11.76
    },
    {
      "date": "2026-06-16",
      "is_forecast": true,
      "surface": {
        "temperature": 23.36,
        "salinity": 37.89,
        "current_speed": 0.022,
        "current_direction": 206.6,
        "oxygen": 244.82,
        "chlorophyll": 0.07,
        "nitrate": 0.33,
        "phosphate": 0.01
      },
      "10m": {
        "temperature": 20.32,
        "salinity": 37.88,
        "current_speed": 0.041,
        "current_direction": 194.0,
        "oxygen": 244.82,
        "chlorophyll": 0.07,
        "nitrate": 0.33,
        "phosphate": 0.01
      },
      "20m": {
        "temperature": 19.3,
        "salinity": 37.93,
        "current_speed": 0.03,
        "current_direction": 180.0,
        "oxygen": 246.49,
        "chlorophyll": 0.08,
        "nitrate": 0.38,
        "phosphate": 0.01
      },
      "30m": {
        "temperature": 17.99,
        "salinity": 37.99,
        "current_speed": 0.022,
        "current_direction": 153.4,
        "oxygen": 252.82,
        "chlorophyll": 0.12,
        "nitrate": 0.17,
        "phosphate": 0.01
      },
      "40m": {
        "temperature": 17.13,
        "salinity": 38.04,
        "current_speed": 0.014,
        "current_direction": 135.0,
        "oxygen": 253.56,
        "chlorophyll": 0.21,
        "nitrate": 0.05,
        "phosphate": 0.01
      },
      "mixed_layer_depth": 11.76
    },
    {
      "date": "2026-06-17",
      "is_forecast": true,
      "surface": {
        "temperature": 23.65,
        "salinity": 37.9,
        "current_speed": 0.058,
        "current_direction": 239.0,
        "oxygen": 243.73,
        "chlorophyll": 0.06,
        "nitrate": 0.32,
        "phosphate": 0.01
      },
      "10m": {
        "temperature": 20.64,
        "salinity": 37.87,
        "current_speed": 0.051,
        "current_direction": 191.3,
        "oxygen": 243.74,
        "chlorophyll": 0.06,
        "nitrate": 0.32,
        "phosphate": 0.01
      },
      "20m": {
        "temperature": 19.72,
        "salinity": 37.92,
        "current_speed": 0.04,
        "current_direction": 180.0,
        "oxygen": 244.16,
        "chlorophyll": 0.07,
        "nitrate": 0.38,
        "phosphate": 0.01
      },
      "30m": {
        "temperature": 18.41,
        "salinity": 37.97,
        "current_speed": 0.032,
        "current_direction": 161.6,
        "oxygen": 250.43,
        "chlorophyll": 0.1,
        "nitrate": 0.22,
        "phosphate": 0.01
      },
      "40m": {
        "temperature": 17.31,
        "salinity": 38.03,
        "current_speed": 0.022,
        "current_direction": 116.6,
        "oxygen": 253.35,
        "chlorophyll": 0.17,
        "nitrate": 0.07,
        "phosphate": 0.01
      },
      "mixed_layer_depth": 11.75
    }
  ],
  "units": {
    "temperature": "°C",
    "salinity": "PSU",
    "current_speed": "m/s",
    "current_direction": "°",
    "oxygen": "mmol/m³",
    "chlorophyll": "mg/m³",
    "nitrate": "mmol/m³",
    "phosphate": "mmol/m³",
    "mixed_layer_depth": "m"
  }
}